pyproject.toml
setup.py
wcoin.py
wtech.py
wtech_api.egg-info/PKG-INFO
wtech_api.egg-info/SOURCES.txt
wtech_api.egg-info/dependency_links.txt
wtech_api.egg-info/requires.txt
wtech_api.egg-info/top_level.txt