Metadata-Version: 2.1
Name: wtech-api
Version: 0.0.1
Summary: Hello There!
Home-page: https://github.com/wangtry3417/WTech.git
Author: Wangtry
Author-email: wangtry3417@gmail.com
